limitcalc/__init__.py
limitcalc/config.py
limitcalc/limitcalc.py
limitcalc-0.0.1.dist-info/METADATA
limitcalc-0.0.1.dist-info/WHEEL
limitcalc-0.0.1.dist-info/top_level.txt
limitcalc-0.0.1.dist-info/RECORD
