Metadata-Version: 2.1
Name: limitcalc
Version: 0.0.1
Summary: Calculate the limit up price and limit down price of a ticker
Home-page: https://github.com/lyenliang/limitcalc
Author: lyenliang
Author-email: lyenliang@gmail.com
License: UNKNOWN
Platform: UNKNOWN
Classifier: Programming Language :: Python :: 3
Classifier: License :: OSI Approved :: MIT License
Classifier: Operating System :: OS Independent
Requires-Python: >=3.6
